pyaisc/__init__.py
pyaisc/v13/__init__.py
pyaisc/v13/b13.py
pyaisc/v13/d13.py
pyaisc/v13/e13.py
pyaisc/v13/f13.py
pyaisc/v13/g13.py
pyaisc/v13/h13.py
pyaisc/v13/i13.py
pyaisc/v14/__init__.py
pyaisc/v14/b14.py
pyaisc/v14/d14.py
pyaisc/v14/e14.py
pyaisc/v14/f14.py
pyaisc/v14/g14.py
pyaisc/v14/h14.py
pyaisc/v14/i14.py
pyaisc/v15/__init__.py
pyaisc/v15/b15.py
pyaisc/v15/d15.py
pyaisc/v15/e15.py
pyaisc/v15/f15.py
pyaisc/v15/g15.py
pyaisc/v15/h15.py
pyaisc/v15/i15.py
pyaisc-0.1.0.dist-info/LICENSE
pyaisc-0.1.0.dist-info/METADATA
pyaisc-0.1.0.dist-info/WHEEL
pyaisc-0.1.0.dist-info/top_level.txt
pyaisc-0.1.0.dist-info/RECORD
