Metadata-Version: 2.1
Name: pyaisc
Version: 0.1.0
Summary: American Institute of Steel Construction in Python
Home-page: https://github.com/mwhit74/pyaisc
Author: MLW
License: MIT
Requires-Python: >=3.6
License-File: LICENSE
